{
    "team": "SK",
    "team_averages": {
        "avg_acs": 202.5,
        "avg_kd": 1.0
    },
    "map_win_rates": {
        "Bind": "50.0%",
        "Corrode": "66.66666666666666%"
    },
    "players": {
        "@your_local_asain_midget": {
            "Riot Id": "YukiForce1#NA1",
            "Rank": "Gold",
            "Average ACS": 146.2,
            "Average K/D": 0.7951807228915663,
            "Most Played Agent": "Omen"
        },
        "@limit7078": {
            "Riot Id": "Limit80#NA1",
            "Rank": "Platinum",
            "Average ACS": 193.2,
            "Average K/D": 0.8977272727272727,
            "Most Played Agent": "Waylay"
        },
        "@haylo995": {
            "Riot Id": "HayLo995#Boss",
            "Rank": "Iron/Bronze",
            "Average ACS": 121.0,
            "Average K/D": 0.5783132530120482,
            "Most Played Agent": "Chamber"
        },
        "@justcallmebot": {
            "Riot Id": "Ophi#blind",
            "Rank": "Immortal 1/2",
            "Average ACS": 312.3333333333333,
            "Average K/D": 1.5862068965517242,
            "Most Played Agent": "Phoenix"
        },
        "@nickjunyor": {
            "Riot Id": "El Psy Kongroo#Skuld",
            "Rank": "Diamond",
            "Average ACS": 266.46153846153845,
            "Average K/D": 1.4943181818181819,
            "Most Played Agent": "Sova"
        }
    }
}